prompt_xmlifier/__init__.py
prompt_xmlifier/__main__.py
prompt_xmlifier/cli.py
prompt_xmlifier/examples.py
prompt_xmlifier/models.py
prompt_xmlifier/platforms.py
prompt_xmlifier/xmlifier.py
prompt_xmlifier-1.0.0.dist-info/licenses/LICENSE
prompt_xmlifier-1.0.0.dist-info/METADATA
prompt_xmlifier-1.0.0.dist-info/WHEEL
prompt_xmlifier-1.0.0.dist-info/entry_points.txt
prompt_xmlifier-1.0.0.dist-info/top_level.txt
prompt_xmlifier-1.0.0.dist-info/RECORD
