Metadata-Version: 2.4
Name: prompt-xmlifier
Version: 1.0.0
Summary: Enterprise-grade prompt structuring tool for Claude - converts plain text prompts to XML-tagged format
Author-email: Fuad Oñate <fu.onate@duocuc.cl>
License: MIT
Project-URL: Documentation, https://platform.claude.com/docs/en/build-with-claude/prompt-engineering/use-xml-tags
Keywords: claude,anthropic,prompt-engineering,xml,llm,ai
Classifier: Development Status :: 4 - Beta
Classifier: Intended Audience :: Developers
Classifier: License :: OSI Approved :: MIT License
Classifier: Operating System :: OS Independent
Classifier: Programming Language :: Python :: 3
Classifier: Programming Language :: Python :: 3.10
Classifier: Programming Language :: Python :: 3.11
Classifier: Programming Language :: Python :: 3.12
Classifier: Topic :: Software Development :: Libraries :: Python Modules
Classifier: Topic :: Text Processing :: Markup :: XML
Requires-Python: >=3.10
License-File: LICENSE
Provides-Extra: dev
Requires-Dist: pytest>=7.0; extra == "dev"
Requires-Dist: pytest-cov>=4.0; extra == "dev"
Requires-Dist: mypy>=1.0; extra == "dev"
Requires-Dist: ruff>=0.1.0; extra == "dev"
Dynamic: license-file
